onpage_hub_api_client/Configuration.py
onpage_hub_api_client/Message.py
onpage_hub_api_client/OnPageHubApi.py
onpage_hub_api_client/__init__.py
OnPage_HUB_API_Client-0.1.1.dist-info/DESCRIPTION.rst
OnPage_HUB_API_Client-0.1.1.dist-info/METADATA
OnPage_HUB_API_Client-0.1.1.dist-info/metadata.json
OnPage_HUB_API_Client-0.1.1.dist-info/RECORD
OnPage_HUB_API_Client-0.1.1.dist-info/top_level.txt
OnPage_HUB_API_Client-0.1.1.dist-info/WHEEL
