Metadata-Version: 2.0
Name: OnPage-HUB-API-Client
Version: 0.1.1
Summary: Send Page to pager using OnPage HUB API
Home-page: http://www.onpage.com
Author: Onset Technology
Author-email: support@onsettechnology.com
License: LICENSE
Platform: UNKNOWN
Requires-Dist: suds (>=0.4)
